Metadata-Version: 2.1
Name: FreeAlchemist
Version: 0.7
Summary: FreeAlchemist is a figure block game written in Python where you have to connect blocks
Home-page: https://github.com/dakk/FreeAlchemist
Author: Davide Gessa
Author-email: gessadavide@gmail.com
License: UNKNOWN
Platform: UNKNOWN
License-File: LICENSE
